{
	"presetOptions": {
		"tileTransitionSize": 2
	},
	"ignoreTiles": [ 
		".",
		"D",
		"4",
		"7",
		"6",
		"Q",
		"b"
	],
	"tiles": [
	{
		"display": "Wall Block",
		"tileName": "blocking1",
		"tileCode": "M",
		"tileTypes": [
		{
			"tileParts": {
				"top": 528,
				"mid": 1000,
				"bot": 237,
				"left": 0,
				"right": 0
			},
			"asset": "wood_block.svg",
			"sound": "wood.ogg"
		},
		{
			"tileParts": {
				"top": 512,
				"mid": 1000,
				"bot": 291,
				"left": 0,
				"right": 0
			},
			"asset": "stone_block.svg"
		},
		{
			"tileParts": {
				"top": 500,
				"mid": 1000,
				"bot": 234,
				"left": 0,
				"right": 0
			},
			"asset": "ice_block.svg"
		},
		{
			"tileParts": {
				"top": 482,
				"mid": 1000,
				"bot": 283,
				"left": 0,
				"right": 0
			},
			"asset": "wall_block.svg"
		},
		{
			"tileParts": {
				"top": 500,
				"mid": 1000,
				"bot": 243,
				"left": 0,
				"right": 0
			},
			"asset": "wall_block_red.svg"
		},
		{
			"tileParts": {
				"top": 500,
				"mid": 1000,
				"bot": 300,
				"left": 0,
				"right": 0
			},
			"asset": "wall_block_gray.svg"
		},
		{
			"tileParts": {
				"top": 600,
				"mid": 1000,
				"bot": 300,
				"left": 0,
				"right": 0
			},
			"asset": "metal_box.svg"
		},
		{
			"tileParts": {
				"top": 500,
				"mid": 1000,
				"bot": 300,
				"left": 0,
				"right": 0
			},
			"asset": "arcade_wall.svg"
		},
		{
			"tileParts": {
				"top": 500,
				"mid": 1000,
				"bot": 300,
				"left": 0,
				"right": 0
			},
			"asset": "sandstone_star.svg"
		},
		{
			"tileParts": {
				"top": 550,
				"mid": 1000,
				"bot": 300,
				"left": 0,
				"right": 0
			},
			"asset": "apartment.svg"
		},
		{
			"tileParts": {
				"top": 500,
				"mid": 1000,
				"bot": 300,
				"left": 0,
				"right": 0
			},
			"asset": "merch_closed.svg"
		}
		]
	},
	{
		"tileName": "blocking2",
		"tileCode": "X",
		"tileTypes": [
		{
			"tileParts": {
				"top": 405,
				"mid": 1000,
				"bot": 280,
				"left": 0,
				"right": 20
			},
			"asset": "crystal_magenta.svg"
		},
		{
			"tileParts": {
				"top": 528,
				"mid": 1000,
				"bot": 237,
				"left": 0,
				"right": 0
			},
			"asset": "grass_block.svg"
		},
		{
			"tileParts": {
				"top": 528,
				"mid": 1000,
				"bot": 237,
				"left": 0,
				"right": 0
			},
			"asset": "wood_block.svg"
		},
		{
			"tileParts": {
				"top": 405,
				"mid": 1000,
				"bot": 280,
				"left": 0,
				"right": 20
			},
			"asset": "crystal_red.svg"
		},
		{
			"tileParts": {
				"top": 544,
				"mid": 1000,
				"bot": 243,
				"left": 0,
				"right": 0
			},
			"asset": "tires.svg"
		},
		{
			"tileParts": {
				"top": 500,
				"mid": 1000,
				"bot": 300,
				"left": 0,
				"right": 0
			},
			"asset": "tombstone.svg"
		},
		{
			"tileParts": {
				"top": 550,
				"mid": 1000,
				"bot": 300,
				"left": 0,
				"right": 0
			},
			"asset": "chest.svg"
		},
		{
			"tileParts": {
				"top": 450,
				"mid": 1000,
				"bot": 300,
				"left": 0,
				"right": 0
			},
			"asset": "yellow_block.svg"
		},
		{
			"tileParts": {
				"top": 500,
				"mid": 1000,
				"bot": 300,
				"left": 0,
				"right": 0
			},
			"asset": "sandstone_rombus.svg"
		},
		{
			"tileParts": {
				"top": 600,
				"mid": 1000,
				"bot": 300,
				"left": 0,
				"right": 0
			},
			"asset": "factory.svg"
		},
		{
			"tileParts": {
				"top": 300,
				"mid": 1000,
				"bot": 300,
				"left": 0,
				"right": 0
			},
			"asset": "merch_display.svg"
		}
		]
	},
	{
		"tileName": "blocking3",
		"tileCode": "Y",
		"tileTypes": [
		{
			"tileParts": {
				"top": 517,
				"mid": 1000,
				"bot": 246,
				"left": 0,
				"right": 0
			},
			"asset": "crate.svg"
		},
		{
			"tileParts": {
				"top": 499,
				"mid": 1000,
				"bot": 245,
				"left": 0,
				"right": 0
			},
			"asset": "present_box.svg"
		},
		{
			"tileParts": {
				"top": 500,
				"mid": 1000,
				"bot": 243,
				"left": 0,
				"right": 0
			},
			"asset": "crate_orange.svg"
		},
		{
			"tileParts": {
				"top": 500,
				"mid": 1000,
				"bot": 300,
				"left": 0,
				"right": 0
			},
			"asset": "crate_red.svg"
		},
		{
			"tileParts": {
				"top": 500,
				"mid": 1000,
				"bot": 300,
				"left": 0,
				"right": 0
			},
			"asset": "orange_wall.svg"
		},
		{
			"tileParts": {
				"top": 500,
				"mid": 1000,
				"bot": 300,
				"left": 50,
				"right": 50
			},
			"asset": "tent.svg"
		},
		{
			"tileParts": {
				"top": 350,
				"mid": 1000,
				"bot": 300,
				"left": 0,
				"right": 0
			},
			"asset": "warehouse.svg"
		},
		{
			"tileParts": {
				"top": 400,
				"mid": 1000,
				"bot": 300,
				"left": 0,
				"right": 0
			},
			"asset": "merch_crate.svg"
		}
		]
	},
	{
		"tileName": "blocking4",
		"tileCode": "C",
		"tileTypes": [
		{
			"tileParts": {
				"top": 439,
				"mid": 1000,
				"bot": 266,
				"left": 0,
				"right": 0
			},
			"asset": "barrel.svg"
		},
		{
			"tileParts": {
				"top": 539,
				"mid": 1000,
				"bot": 327,
				"left": 0,
				"right": 0
			},
			"asset": "present_barrel.svg"
		},
		{
			"tileParts": {
				"top": 566,
				"mid": 1000,
				"bot": 243,
				"left": 0,
				"right": 0
			},
			"asset": "metal_barrel.svg"
		},
		{
			"tileParts": {
				"top": 400,
				"mid": 1000,
				"bot": 300,
				"left": 0,
				"right": 0
			},
			"asset": "red_barrel.svg"
		},
		{
			"tileParts": {
				"top": 600,
				"mid": 1000,
				"bot": 300,
				"left": 0,
				"right": 0
			},
			"asset": "orange_barrel.svg"
		},
		{
			"tileParts": {
				"top": 400,
				"mid": 1000,
				"bot": 300,
				"left": 0,
				"right": 0
			},
			"asset": "basket.svg"
		},
		{
			"tileParts": {
				"top": 600,
				"mid": 1000,
				"bot": 300,
				"left": 0,
				"right": 0
			},
			"asset": "office.svg"
		}
		]
	},
	{
		"tileName": "forest",
		"tileCode": "F",
		"tileTypes": [
		{
			"tileParts": {
				"top": 447,
				"mid": 1000,
				"bot": 296,
				"left": 0,
				"right": 0
			},
			"color": "green",
			"asset": "grass_green.svg",
			"tileTransitions": true
		},
		{
			"tileParts": {
				"top": 447,
				"mid": 1000,
				"bot": 296,
				"left": 0,
				"right": 0
			},
			"color": "cyan",
			"asset": "grass_cyan.svg",
			"tileTransitions": true
		},
		{
			"tileParts": {
				"top": 447,
				"mid": 1000,
				"bot": 296,
				"left": 0,
				"right": 0
			},
			"color": "yellow",
			"asset": "grass_yellow.svg",
			"tileTransitions": true
		},
		{
			"tileParts": {
				"top": 447,
				"mid": 1000,
				"bot": 296,
				"left": 0,
				"right": 0
			},
			"color": "blue",
			"asset": "grass_blue.svg",
			"tileTransitions": true
		},
		{
			"tileParts": {
				"top": 447,
				"mid": 1000,
				"bot": 296,
				"left": 0,
				"right": 0
			},
			"color": "blue",
			"asset": "grass_neon_blue.svg",
			"tileTransitions": true
		},
		{
			"tileParts": {
				"top": 500,
				"mid": 1000,
				"bot": 300,
				"left": 0,
				"right": 0
			},
			"color": "blue gradient",
			"asset": "grass_blue_fade.svg",
			"tileTransitions": true
		},
		{
			"tileParts": {
				"top": 500,
				"mid": 1000,
				"bot": 300,
				"left": 0,
				"right": 0
			},
			"color": "green round",
			"asset": "grass_green_round.svg",
			"tileTransitions": true
		},
		{
			"tileParts": {
				"top": 500,
				"mid": 1000,
				"bot": 300,
				"left": 0,
				"right": 0
			},
			"color": "pink",
			"asset": "grass_pink.svg",
			"tileTransitions": true
		},
		{
			"tileParts": {
				"top": 550,
				"mid": 1000,
				"bot": 300,
				"left": 50,
				"right": 50
			},
			"color": "forest",
			"asset": "forest.svg",
			"tileTransitions": true
		},
		{
			"tileParts": {
				"top": 500,
				"mid": 1000,
				"bot": 300,
				"left": 0,
				"right": 0
			},
			"color": "dull green",
			"asset": "grass_dull.svg",
			"tileTransitions": true
		}
		]
	},
	{
		"tileName": "respawningWall",
		"tileCode": "T",
		"tileTypes": [
		{
			"tileParts": {
				"top": 597,
				"mid": 1000,
				"bot": 243,
				"left": 65,
				"right": 112
			},
			"asset": "cactus.svg",
			"orderHor": 1
		},
		{
			"tileParts": {
				"top": 386,
				"mid": 1000,
				"bot": 327,
				"left": 7,
				"right": 4
			},
			"asset": "mushroom.svg"
		},
		{
			"tileParts": {
				"top": 464,
				"mid": 1000,
				"bot": 136,
				"left": 0,
				"right": 0
			},
			"asset": "tree.svg"
		},
		{
			"tileParts": {
				"top": 875,
				"mid": 1000,
				"bot": 331,
				"left": 3,
				"right": 3
			},
			"asset": "sapling.svg"
		},
		{
			"tileParts": {
				"top": 400,
				"mid": 1000,
				"bot": 300,
				"left": 100,
				"right": 100
			},
			"asset": "stump.svg"
		},
		{
			"tileParts": {
				"top": 400,
				"mid": 1000,
				"bot": 300,
				"left": 0,
				"right": 0
			},
			"asset": "ship_barrel.svg"
		},
		{
			"tileParts": {
				"top": 400,
				"mid": 1000,
				"bot": 300,
				"left": 0,
				"right": 0
			},
			"asset": "road_sign.svg"
		},
		{
			"tileParts": {
				"top": 550,
				"mid": 1000,
				"bot": 300,
				"left": 75,
				"right": 75
			},
			"asset": "pot.svg"
		},
		{
			"tileParts": {
				"top": 500,
				"mid": 1000,
				"bot": 300,
				"left": 50,
				"right": 50
			},
			"asset": "cargo.svg"
		},
		{
			"tileParts": {
				"top": 522,
				"mid": 1000,
				"bot": 300,
				"left": 50,
				"right": 50
			},
			"asset": "old_tv.svg"
		}
		]
	},
	{
		"tileName": "blockingDestroyableWithWeapon",
		"tileCode": "B",
		"tileTypes": [
		{
			"tileParts": {
				"top": 392,
				"mid": 1000,
				"bot": 190,
				"left": 0,
				"right": 0
			},
			"asset": "vase.svg"
		},
		{
			"tileParts": {
				"top": 0,
				"mid": 980,
				"bot": 98,
				"left": 8,
				"right": 0
			},
			"asset": "skull.svg"
		},
		{
			"tileParts": {
				"top": 265,
				"mid": 1000,
				"bot": 91,
				"left": 0,
				"right": 0
			},
			"asset": "present_mini.svg"
		},
		{
			"tileParts": {
				"top": 351,
				"mid": 1000,
				"bot": 156,
				"left": 0,
				"right": 0
			},
			"asset": "cone.svg"
		},
		{
			"tileParts": {
				"top": 350,
				"mid": 1000,
				"bot": 150,
				"left": 0,
				"right": 0
			},
			"asset": "candles.svg"
		},
		{
			"tileParts": {
				"top": -50,
				"mid": 1000,
				"bot": 0,
				"left": -50,
				"right": 0
			},
			"asset": "round_shot.svg"
		},
		{
			"tileParts": {
				"top": 150,
				"mid": 1000,
				"bot": 0,
				"left": 0,
				"right": 0
			},
			"asset": "vending_machines.svg"
		},
		{
			"tileParts": {
				"top": 550,
				"mid": 1000,
				"bot": 400,
				"left": -50,
				"right": -50
			},
			"asset": "balloon.svg"
		}
		]
	},
	{
		"tileName": "fence",
		"tileCode": "N",
		"tileTypes": [
		{
			"tileParts": {
				"top": 127,
				"mid": 1000,
				"bot": 242,
				"left": 45,
				"right": 45
			},
			"asset": "fence_hor.svg",
			"orderHor": 1
		},
		{
			"tileParts": {
				"top": 601,
				"mid": 1000,
				"bot": 243,
				"left": 0,
				"right": 0
			},
			"asset": "fence_ver.svg"
		},
		{
			"tileParts": {
				"top": 517,
				"mid": 1000,
				"bot": 243,
				"left": 45,
				"right": 45
			},
			"asset": "fence_cor.svg",
			"orderHor": 1
		},
		{
			"tileParts": {
				"top": 317,
				"mid": 1000,
				"bot": 243,
				"left": 44,
				"right": 44
			},
			"asset": "fence_hor_lunar.svg",
			"orderHor": 1
		},
		{
			"tileParts": {
				"top": 602,
				"mid": 1000,
				"bot": 243,
				"left": 0,
				"right": 0
			},
			"asset": "fence_ver_lunar.svg"
		},
		{
			"tileParts": {
				"top": 517,
				"mid": 1000,
				"bot": 243,
				"left": 45,
				"right": 45
			},
			"asset": "fence_cor_lunar.svg",
			"orderHor": 1
		},
		{
			"tileParts": {
				"top": 500,
				"mid": 1000,
				"bot": 0,
				"left": 0,
				"right": 0
			},
			"asset": "neon_railing_hor.svg"
		},
		{
			"tileParts": {
				"top": 650,
				"mid": 1000,
				"bot": 0,
				"left": 0,
				"right": 0
			},
			"asset": "neon_railing_ver.svg"
		},
		{
			"tileParts": {
				"top": 500,
				"mid": 1000,
				"bot": 0,
				"left": 2,
				"right": 0
			},
			"asset": "neon_railing_r.svg",
			"orderHor": 1
		},
		{
			"tileParts": {
				"top": 500,
				"mid": 1000,
				"bot": 0,
				"left": 0,
				"right": 2
			},
			"asset": "neon_railing_l.svg",
			"orderHor": 1
		},
		{
			"tileParts": {
				"top": 650,
				"mid": 1000,
				"bot": 0,
				"left": 0,
				"right": 0
			},
			"asset": "neon_railing_t.svg",
			"orderHor": 1
		},
		{
			"tileParts": {
				"top": 440,
				"mid": 1000,
				"bot": 0,
				"left": 0,
				"right": 0
			},
			"asset": "neon_railing_b.svg",
			"orderHor": 1
		},
		{
			"tileParts": {
				"top": 500,
				"mid": 1000,
				"bot": 0,
				"left": 0,
				"right": 0
			},
			"asset": "neon_railing_tr.svg",
			"orderHor": 1
		},
		{
			"tileParts": {
				"top": 500,
				"mid": 1000,
				"bot": 0,
				"left": 0,
				"right": 0
			},
			"asset": "neon_railing_tl.svg",
			"orderHor": 1
		},
		{
			"tileParts": {
				"top": 650,
				"mid": 1000,
				"bot": 0,
				"left": 0,
				"right": 0
			},
			"asset": "neon_railing_br.svg",
			"orderHor": 1
		},
		{
			"tileParts": {
				"top": 650,
				"mid": 1000,
				"bot": 0,
				"left": 0,
				"right": 0
			},
			"asset": "neon_railing_bl.svg",
			"orderHor": 1
		},
		{
			"tileParts": {
				"top": 550,
				"mid": 1000,
				"bot": 300,
				"left": 50,
				"right": 50
			},
			"asset": "fence_hor_mor.svg",
			"orderHor": 1
		},
		{
			"tileParts": {
				"top": 750,
				"mid": 1000,
				"bot": 300,
				"left": -150,
				"right": -150
			},
			"asset": "fence_ver_mor.svg",
			"orderHor": 1
		},
		{
			"tileParts": {
				"top": 550,
				"mid": 1000,
				"bot": 300,
				"left": 0,
				"right": 0
			},
			"asset": "fence_cor_mor.svg",
			"orderHor": 1
		},
		{
			"tileParts": {
				"top": 450,
				"mid": 1000,
				"bot": 0,
				"left": 0,
				"right": 0
			},
			"asset": "ship_railing_hor.svg"
		},
		{
			"tileParts": {
				"top": -50,
				"mid": 1000,
				"bot": 0,
				"left": -150,
				"right": 0
			},
			"asset": "ship_railing_ver.svg"
		},
		{
			"tileParts": {
				"top": 450,
				"mid": 1000,
				"bot": 0,
				"left": 0,
				"right": 0
			},
			"asset": "ship_railing_r.svg",
			"orderHor": 1
		},
		{
			"tileParts": {
				"top": 450,
				"mid": 1000,
				"bot": 0,
				"left": 0,
				"right": 0
			},
			"asset": "ship_railing_l.svg",
			"orderHor": 1
		},
		{
			"tileParts": {
				"top": -50,
				"mid": 1000,
				"bot": 0,
				"left": -150,
				"right": 0
			},
			"asset": "ship_railing_b.svg",
			"orderHor": 1
		},
		{
			"tileParts": {
				"top": -250,
				"mid": 1000,
				"bot": 0,
				"left": -150,
				"right": 0
			},
			"asset": "ship_railing_t.svg",
			"orderHor": 1
		},
		{
			"tileParts": {
				"top": 450,
				"mid": 1000,
				"bot": 50,
				"left": -150,
				"right": 0
			},
			"asset": "ship_railing_tr.svg",
			"orderHor": 1
		},
		{
			"tileParts": {
				"top": 450,
				"mid": 1000,
				"bot": 50,
				"left": 0,
				"right": 0
			},
			"asset": "ship_railing_tl.svg",
			"orderHor": 1
		},
		{
			"tileParts": {
				"top": 600,
				"mid": 1000,
				"bot": 0,
				"left": -150,
				"right": 0
			},
			"asset": "ship_railing_br.svg",
			"orderHor": 1
		},
		{
			"tileParts": {
				"top": 600,
				"mid": 1000,
				"bot": 0,
				"left": 0,
				"right": 0
			},
			"asset": "ship_railing_bl.svg",
			"orderHor": 1
		},
		{
			"tileParts": {
				"top": 200,
				"mid": 1000,
				"bot": 0,
				"left": -150,
				"right": 0
			},
			"asset": "ship_railing_to.svg",
			"orderHor": 1
		},
		{
			"tileParts": {
				"top": 800,
				"mid": 1000,
				"bot": 300,
				"left": 150,
				"right": 150
			},
			"asset": "arcade_fence_corner.svg",
			"orderHor": 2
		},
		{
			"tileParts": {
				"top": 400,
				"mid": 1000,
				"bot": 300,
				"left": 50,
				"right": 50
			},
			"asset": "arcade_fence_hor.svg",
			"orderHor": 1
		},
		{
			"tileParts": {
				"top": 450,
				"mid": 1000,
				"bot": 0,
				"left": -125,
				"right": -125
			},
			"asset": "arcade_fence_ver.svg",
			"orderHor": 1
		},
		{
			"tileParts": {
				"top": 550,
				"mid": 1000,
				"bot": 300,
				"left": 0,
				"right": 0
			},
			"asset": "wall_sand_hor.svg",
			"orderHor": 1
		},
		{
			"tileParts": {
				"top": 600,
				"mid": 1000,
				"bot": -100,
				"left": -150,
				"right": -150
			},
			"asset": "wall_sand_ver.svg",
			"orderHor": 1
		},
		{
			"tileParts": {
				"top": 550,
				"mid": 1000,
				"bot": 300,
				"left": 0,
				"right": 0
			},
			"asset": "wall_sand_r.svg",
			"orderHor": 1
		},
		{
			"tileParts": {
				"top": 550,
				"mid": 1000,
				"bot": 300,
				"left": 0,
				"right": 0
			},
			"asset": "wall_sand_l.svg",
			"orderHor": 1
		},
		{
			"tileParts": {
				"top": 600,
				"mid": 1000,
				"bot": -200,
				"left": -150,
				"right": -150
			},
			"asset": "wall_sand_b.svg",
			"orderHor": 1
		},
		{
			"tileParts": {
				"top": 600,
				"mid": 1000,
				"bot": -100,
				"left": -150,
				"right": -150
			},
			"asset": "wall_sand_t.svg",
			"orderHor": 1
		},
		{
			"tileParts": {
				"top": 550,
				"mid": 1000,
				"bot": 300,
				"left": -150,
				"right": 0
			},
			"asset": "wall_sand_tr.svg",
			"orderHor": 1
		},
		{
			"tileParts": {
				"top": 550,
				"mid": 1000,
				"bot": 300,
				"left": 0,
				"right": -150
			},
			"asset": "wall_sand_tl.svg",
			"orderHor": 1
		},
		{
			"tileParts": {
				"top": 1000,
				"mid": 1000,
				"bot": 300,
				"left": -150,
				"right": 0
			},
			"asset": "wall_sand_br.svg",
			"orderHor": 1
		},
		{
			"tileParts": {
				"top": 1000,
				"mid": 1000,
				"bot": 300,
				"left": 0,
				"right": -150
			},
			"asset": "wall_sand_bl.svg",
			"orderHor": 1
		},
		{
			"tileParts": {
				"top": 550,
				"mid": 1000,
				"bot": 400,
				"left": 0,
				"right": 0
			},
			"asset": "building_long_hor.svg",
			"orderHor": 1
		},
		{
			"tileParts": {
				"top": 500,
				"mid": 1000,
				"bot": -500,
				"left": -150,
				"right": -150
			},
			"asset": "building_long_ver.svg",
			"orderHor": 1
		},
		{
			"tileParts": {
				"top": 550,
				"mid": 1000,
				"bot": 400,
				"left": 0,
				"right": 0
			},
			"asset": "building_long_r.svg",
			"orderHor": 1
		},
		{
			"tileParts": {
				"top": 550,
				"mid": 1000,
				"bot": 400,
				"left": 0,
				"right": 0
			},
			"asset": "building_long_l.svg",
			"orderHor": 1
		},
		{
			"tileParts": {
				"top": 500,
				"mid": 1000,
				"bot": -200,
				"left": -150,
				"right": -150
			},
			"asset": "building_long_b.svg",
			"orderHor": 1
		},
		{
			"tileParts": {
				"top": 500,
				"mid": 1000,
				"bot": -500,
				"left": -150,
				"right": -150
			},
			"asset": "building_long_t.svg",
			"orderHor": 1
		},
		{
			"tileParts": {
				"top": 450,
				"mid": 1000,
				"bot": 400,
				"left": -150,
				"right": 0
			},
			"asset": "building_long_tr.svg",
			"orderHor": 1
		},
		{
			"tileParts": {
				"top": 450,
				"mid": 1000,
				"bot": 400,
				"left": 0,
				"right": -150
			},
			"asset": "building_long_tl.svg",
			"orderHor": 1
		},
		{
			"tileParts": {
				"top": 900,
				"mid": 1000,
				"bot": 400,
				"left": -150,
				"right": 0
			},
			"asset": "building_long_br.svg",
			"orderHor": 1
		},
		{
			"tileParts": {
				"top": 900,
				"mid": 1000,
				"bot": 400,
				"left": 0,
				"right": -150
			},
			"asset": "building_long_bl.svg",
			"orderHor": 1
		},
		{
			"tileParts": {
				"top": 450,
				"mid": 1000,
				"bot": 0,
				"left": 0,
				"right": 0
			},
			"asset": "gift_fence_hor.svg"
		},
		{
			"tileParts": {
				"top": -50,
				"mid": 1000,
				"bot": 0,
				"left": -150,
				"right": 0
			},
			"asset": "gift_fence_ver.svg"
		},
		{
			"tileParts": {
				"top": 450,
				"mid": 1000,
				"bot": 0,
				"left": 0,
				"right": 0
			},
			"asset": "gift_fence_r.svg",
			"orderHor": 1
		},
		{
			"tileParts": {
				"top": 450,
				"mid": 1000,
				"bot": 0,
				"left": 0,
				"right": 0
			},
			"asset": "gift_fence_l.svg",
			"orderHor": 1
		},
		{
			"tileParts": {
				"top": -50,
				"mid": 1000,
				"bot": 0,
				"left": -150,
				"right": 0
			},
			"asset": "gift_fence_b.svg",
			"orderHor": 1
		},
		{
			"tileParts": {
				"top": -250,
				"mid": 1000,
				"bot": 0,
				"left": -150,
				"right": 0
			},
			"asset": "gift_fence_t.svg",
			"orderHor": 1
		},
		{
			"tileParts": {
				"top": 450,
				"mid": 1000,
				"bot": 50,
				"left": -150,
				"right": 0
			},
			"asset": "gift_fence_tr.svg",
			"orderHor": 1
		},
		{
			"tileParts": {
				"top": 450,
				"mid": 1000,
				"bot": 50,
				"left": 0,
				"right": 0
			},
			"asset": "gift_fence_tl.svg",
			"orderHor": 1
		},
		{
			"tileParts": {
				"top": 600,
				"mid": 1000,
				"bot": 0,
				"left": -150,
				"right": 0
			},
			"asset": "gift_fence_br.svg",
			"orderHor": 1
		},
		{
			"tileParts": {
				"top": 600,
				"mid": 1000,
				"bot": 0,
				"left": 0,
				"right": 0
			},
			"asset": "gift_fence_bl.svg",
			"orderHor": 1
		},
		{
			"tileParts": {
				"top": 200,
				"mid": 1000,
				"bot": 0,
				"left": -150,
				"right": 0
			},
			"asset": "gift_fence_to.svg",
			"orderHor": 1
		}
		],
		"tileLinks": {
			"rules": [
			{
				"condition": "***11***",
				"requiredBiome": 15,
				"changeTileType": 54
			},
			{
				"condition": "*1****1*",
				"requiredBiome": 15,
				"changeTileType": 55
			},
			{
				"condition": "*0*01*0*",
				"requiredBiome": 15,
				"changeTileType": 56
			},
			{
				"condition": "*0*10*0*",
				"requiredBiome": 15,
				"changeTileType": 57
			},
			{
				"condition": "*1*00*0*",
				"requiredBiome": 15,
				"changeTileType": 58
			},
			{
				"condition": "*0*00*1*",
				"requiredBiome": 15,
				"changeTileType": 59
			},
			{
				"condition": "*0*01*1*",
				"requiredBiome": 15,
				"changeTileType": 60
			},
			{
				"condition": "*0*10*1*",
				"requiredBiome": 15,
				"changeTileType": 61
			},
			{
				"condition": "*1*01*0*",
				"requiredBiome": 15,
				"changeTileType": 62
			},
			{
				"condition": "*1*10*0*",
				"requiredBiome": 15,
				"changeTileType": 63
			},
			{
				"condition": "***11***",
				"requiredBiome": 14,
				"changeTileType": 44
			},
			{
				"condition": "*1****1*",
				"requiredBiome": 14,
				"changeTileType": 45
			},
			{
				"condition": "*0*01*0*",
				"requiredBiome": 14,
				"changeTileType": 46
			},
			{
				"condition": "*0*10*0*",
				"requiredBiome": 14,
				"changeTileType": 47
			},
			{
				"condition": "*1*00*0*",
				"requiredBiome": 14,
				"changeTileType": 48
			},
			{
				"condition": "*0*00*1*",
				"requiredBiome": 14,
				"changeTileType": 49
			},
			{
				"condition": "*0*01*1*",
				"requiredBiome": 14,
				"changeTileType": 50
			},
			{
				"condition": "*0*10*1*",
				"requiredBiome": 14,
				"changeTileType": 51
			},
			{
				"condition": "*1*01*0*",
				"requiredBiome": 14,
				"changeTileType": 52
			},
			{
				"condition": "*1*10*0*",
				"requiredBiome": 14,
				"changeTileType": 53
			},
			{
				"condition": "***11***",
				"requiredBiome": 13,
				"changeTileType": 34
			},
			{
				"condition": "*1****1*",
				"requiredBiome": 13,
				"changeTileType": 35
			},
			{
				"condition": "*0*01*0*",
				"requiredBiome": 13,
				"changeTileType": 36
			},
			{
				"condition": "*0*10*0*",
				"requiredBiome": 13,
				"changeTileType": 37
			},
			{
				"condition": "*1*00*0*",
				"requiredBiome": 13,
				"changeTileType": 38
			},
			{
				"condition": "*0*00*1*",
				"requiredBiome": 13,
				"changeTileType": 39
			},
			{
				"condition": "*0*01*1*",
				"requiredBiome": 13,
				"changeTileType": 40
			},
			{
				"condition": "*0*10*1*",
				"requiredBiome": 13,
				"changeTileType": 41
			},
			{
				"condition": "*1*01*0*",
				"requiredBiome": 13,
				"changeTileType": 42
			},
			{
				"condition": "*1*10*0*",
				"requiredBiome": 13,
				"changeTileType": 43
			},
			{
				"condition": "***11***",
				"requiredBiome": 12,
				"changeTileType": 32
			},
			{
				"condition": "*1****1*",
				"requiredBiome": 12,
				"changeTileType": 33
			},
			{
				"condition": "*0****1*",
				"requiredBiome": 12,
				"changeTileType": 31
			},
			{
				"condition": "*1****0*",
				"requiredBiome": 12,
				"changeTileType": 31
			},
			{
				"condition": "***01***",
				"requiredBiome": 12,
				"changeTileType": 31
			},
			{
				"condition": "***10***",
				"requiredBiome": 12,
				"changeTileType": 31
			},
			{
				"condition": "***11***",
				"requiredBiome": 11,
				"changeTileType": 32
			},
			{
				"condition": "*1****1*",
				"requiredBiome": 11,
				"changeTileType": 33
			},
			{
				"condition": "*0****1*",
				"requiredBiome": 11,
				"changeTileType": 31
			},
			{
				"condition": "*1****0*",
				"requiredBiome": 11,
				"changeTileType": 31
			},
			{
				"condition": "***01***",
				"requiredBiome": 11,
				"changeTileType": 31
			},
			{
				"condition": "***10***",
				"requiredBiome": 11,
				"changeTileType": 31
			},
			{
				"condition": "*0*00010",
				"requiredBiome": 10,
				"changeTileType": 25
			},
			{
				"condition": "*0*11*0*",
				"requiredBiome": 10,
				"changeTileType": 20
			},
			{
				"condition": "*1*00*1*",
				"requiredBiome": 10,
				"changeTileType": 21
			},
			{
				"condition": "*0*01*0*",
				"requiredBiome": 10,
				"changeTileType": 22
			},
			{
				"condition": "*0*10*0*",
				"requiredBiome": 10,
				"changeTileType": 23
			},
			{
				"condition": "*1*00*0*",
				"requiredBiome": 10,
				"changeTileType": 24
			},
			{
				"condition": "*0*01*1*",
				"requiredBiome": 10,
				"changeTileType": 26
			},
			{
				"condition": "*0*10*1*",
				"requiredBiome": 10,
				"changeTileType": 27
			},
			{
				"condition": "*1*01*0*",
				"requiredBiome": 10,
				"changeTileType": 28
			},
			{
				"condition": "*1*10*0*",
				"requiredBiome": 10,
				"changeTileType": 29
			},
			{
				"condition": "*0*00*1*",
				"requiredBiome": 10,
				"changeTileType": 30
			},
			{
				"condition": "***11***",
				"requiredBiome": 9,
				"changeTileType": 17
			},
			{
				"condition": "*1****1*",
				"requiredBiome": 9,
				"changeTileType": 18
			},
			{
				"condition": "*0****1*",
				"requiredBiome": 9,
				"changeTileType": 19
			},
			{
				"condition": "*1****0*",
				"requiredBiome": 9,
				"changeTileType": 19
			},
			{
				"condition": "***01***",
				"requiredBiome": 9,
				"changeTileType": 19
			},
			{
				"condition": "***10***",
				"requiredBiome": 9,
				"changeTileType": 19
			},
			{
				"condition": "***11***",
				"requiredBiome": 8,
				"changeTileType": 7
			},
			{
				"condition": "*1****1*",
				"requiredBiome": 8,
				"changeTileType": 8
			},
			{
				"condition": "*0*01*0*",
				"requiredBiome": 8,
				"changeTileType": 9
			},
			{
				"condition": "*0*10*0*",
				"requiredBiome": 8,
				"changeTileType": 10
			},
			{
				"condition": "*1*00*0*",
				"requiredBiome": 8,
				"changeTileType": 11
			},
			{
				"condition": "*0*00*1*",
				"requiredBiome": 8,
				"changeTileType": 12
			},
			{
				"condition": "*0*01*1*",
				"requiredBiome": 8,
				"changeTileType": 13
			},
			{
				"condition": "*0*10*1*",
				"requiredBiome": 8,
				"changeTileType": 14
			},
			{
				"condition": "*1*01*0*",
				"requiredBiome": 8,
				"changeTileType": 15
			},
			{
				"condition": "*1*10*0*",
				"requiredBiome": 8,
				"changeTileType": 16
			},
			{
				"condition": "*1****0*",
				"requiredBiome": 7,
				"changeTileType": 6
			},
			{
				"condition": "*0****1*",
				"requiredBiome": 7,
				"changeTileType": 6
			},
			{
				"condition": "***01***",
				"requiredBiome": 7,
				"changeTileType": 6
			},
			{
				"condition": "***10***",
				"requiredBiome": 7,
				"changeTileType": 6
			},
			{
				"condition": "*1****1*",
				"requiredBiome": 7,
				"changeTileType": 5
			},
			{	
				"condition": "*0****0*",
				"requiredBiome": 7,
				"changeTileType": 4
			},
			{
				"condition": "*1****0*",
				"changeTileType": 3
			},
			{
				"condition": "*0****1*",
				"changeTileType": 3
			},
			{
				"condition": "***01***",
				"changeTileType": 3
			},
			{
				"condition": "***10***",
				"changeTileType": 3
			},
			{
				"condition": "*1****1*",
				"changeTileType": 2
			}
			],
			"multipleConditionsCouldApply": false,
			"edgeCase": 1,
			"defaults": {
				"tileType": 1
			}
		}
	},
	{
		"tileName": "water",
		"tileCode": "W",
		"tileTypes": [
		{
			"tileParts": {
				"top": 0,
				"mid": 1000,
				"bot": 0,
				"left": 0,
				"right": 0
			},
			"asset": "?binary?.svg",
			"tileTransitions": true
		}
		],
		"tileLinks": {
			"rules": [
			{
				"condition": "********",
				"requiredBiome": 10,
				"changeFolder": "ship_water"
			},
			{
				"condition": "********",
				"requiredBiome": 9,
				"changeFolder": "green_water"
			},
			{
				"condition": "*0******",
				"changeBinary": [ "0a1", "0a3" ]
			},
			{
				"condition": "***0****",
				"changeBinary": [ "0a1", "0a6" ]
			},
			{
				"condition": "****0***",
				"changeBinary": [ "0a3", "0a8" ]
			},
			{
				"condition": "******0*",
				"changeBinary": [ "0a6", "0a8" ]
			}
			],
			"multipleConditionsCouldApply": true,
			"defaults": {
				"tileType": 1
			},
			"edgeCase": 2,
			"assetFolder": "water"
		}
	},
	{
		"tileName": "player1",
		"tileCode": "1",
		"tileTypes": [
		{
			"tileParts": {
				"top": 334,
				"mid": 1000,
				"bot": 334,
				"left": 334,
				"right": 334
			},
			"asset": "player_blue.svg",
			"order": 1
		},
		{
			"tileParts": {
				"top": 334,
				"mid": 1000,
				"bot": 334,
				"left": 334,
				"right": 334
			},
			"asset": "player_gray.svg",
			"order": 1
		}
		]
	},
	{
		"tileName": "player2",
		"tileCode": "2",
		"tileTypes": [
		{
			"tileParts": {
				"top": 334,
				"mid": 1000,
				"bot": 334,
				"left": 334,
				"right": 334
			},
			"asset": "player_red.svg",
			"order": 1
		},
		{
			"tileParts": {
				"top": 334,
				"mid": 1000,
				"bot": 334,
				"left": 334,
				"right": 334
			},
			"asset": "player_gray.svg",
			"order": 1
		},
		{
			"tileParts": {
				"top": 2000,
				"mid": 1000,
				"bot": 1000,
				"left": 1500,
				"right": 1500
			},
			"asset": "player_big.svg",
			"order": 1
		},
		{
			"tileParts": {
				"top": 2959,
				"mid": 1000,
				"bot": 1842,
				"left": 2380,
				"right": 2380
			},
			"asset": "player_boss.svg",
			"order": 1
		},
		{
			"tileParts": {
				"top": 0,
				"mid": 1000,
				"bot": 0,
				"left": 0,
				"right": 0
			},
			"asset": "nothing.svg"
		},
		{
			"tileParts": {
				"top": 2200,
				"mid": 1000,
				"bot": 2200,
				"left": 2200,
				"right": 2200
			},
			"asset": "mega_spawn.svg",
			"order": 1
		},
		{
			"tileParts": {
				"top": 2200,
				"mid": 1000,
				"bot": 2200,
				"left": 2200,
				"right": 2200
			},
			"asset": "mega_spawn_mod.svg",
			"order": 1
		}
		]
	},
	{
		"tileName": "objective",
		"tileCode": "8",
		"tileTypes": [
		{
			"tileParts": {
				"top": 402,
				"mid": 1000,
				"bot": 481,
				"left": 440,
				"right": 440
			},
			"asset": "mine.svg"
		},
		{
			"tileParts": {
				"top": 1171,
				"mid": 1000,
				"bot": 92,
				"left": 530,
				"right": 529
			},
			"asset": "vault.svg",
			"order": 3
		},
		{
			"tileParts": {
				"top": 866,
				"mid": 1000,
				"bot": 279,
				"left": 97,
				"right": 97
			},
			"asset": "bounty_star.svg"
		},
		{
			"tileParts": {
				"top": 1671,
				"mid": 508,
				"bot": 0,
				"left": 530,
				"right": 529
			},
			"asset": "vault_offset.svg",
			"order": 3
		},
		{
			"tileParts": {
				"top": 349,
				"mid": 1000,
				"bot": 138,
				"left": 162,
				"right": 162
			},
			"asset": "brawlball.svg",
			"order": 2
		},
		{
			"tileParts": {
				"top": 2851,
				"mid": 1000,
				"bot": 0,
				"left": 2829,
				"right": 2829
			},
			"asset": "goal_red.svg",
			"order": 2
		},
		{
			"tileParts": {
				"top": 2534,
				"mid": 1000,
				"bot": 0,
				"left": 2829,
				"right": 2829
			},
			"asset": "goal_blue.svg",
			"order": 2
		},
		{
			"tileParts": {
				"top": 500,
				"mid": 1000,
				"bot": 600,
				"left": 545,
				"right": 545
			},
			"asset": "mine_snow.svg"
		},
		{
			"tileParts": {
				"top": 2021,
				"mid": 1000,
				"bot": 0,
				"left": 411,
				"right": 880
			},
			"asset": "ike_red.svg",
			"order": 3
		},
		{
			"tileParts": {
				"top": 2235,
				"mid": 1000,
				"bot": 0,
				"left": 873,
				"right": 417
			},
			"asset": "ike_blue.svg",
			"order": 3
		},
		{
			"tileParts": {
				"top": 618,
				"mid": 1000,
				"bot": 775,
				"left": 436,
				"right": 702
			},
			"asset": "mine_town.svg",
			"order": 3
		},
		{
			"tileParts": {
				"top": 618,
				"mid": 1000,
				"bot": 775,
				"left": 436,
				"right": 702
			},
			"asset": "mine_retro.svg",
			"order": 3
		},
		{
			"tileParts": {
				"top": 509,
				"mid": 1000,
				"bot": 785,
				"left": 698,
				"right": 608
			},
			"asset": "mine_mortuary.svg",
			"order": 3
		},
		{
			"tileParts": {
				"top": 450,
				"mid": 1000,
				"bot": 750,
				"left": 450,
				"right": 450
			},
			"asset": "mine_ship.svg",
			"order": 3
		},
		{
			"tileParts": {
				"top": 2000,
				"mid": 1000,
				"bot": 0,
				"left": 1500,
				"right": 450
			},
			"asset": "flag_present_red.svg",
			"order": 3
		},
		{
			"tileParts": {
				"top": 2000,
				"mid": 1000,
				"bot": 750,
				"left": 1500,
				"right": 450
			},
			"asset": "flag_present_blue.svg",
			"order": 3
		},
		{
			"tileParts": {
				"top": 3000,
				"mid": 1000,
				"bot": 3000,
				"left": 3000,
				"right": 3000
			},
			"asset": "hot_zone_blue.svg",
			"order": 3
		},
		{
			"tileParts": {
				"top": 250,
				"mid": 1000,
				"bot": 200,
				"left": 150,
				"right": 150
			},
			"asset": "soccerball.svg",
			"order": 3
		},
		{
			"tileParts": {
				"top": 3600,
				"mid": 1000,
				"bot": -450,
				"left": 3000,
				"right": 3000
			},
			"asset": "goal_red_2.svg",
			"order": 3
		},
		{
			"tileParts": {
				"top": 1600,
				"mid": 1000,
				"bot": 200,
				"left": 2925,
				"right": 2925
			},
			"asset": "goal_blue_2.svg",
			"order": 3
		},
		{
			"tileParts": {
				"top": 450,
				"mid": 1000,
				"bot": 750,
				"left": 450,
				"right": 450
			},
			"asset": "mine_bazaar.svg",
			"order": 3
		},
		{
			"tileParts": {
				"top": 3075,
				"mid": 1000,
				"bot": 3075,
				"left": 3075,
				"right": 3075
			},
			"asset": "hot_zone_both.svg",
			"order": 3
		},
		{
			"tileParts": {
				"top": 625,
				"mid": 1000,
				"bot": 775,
				"left": 587,
				"right": 588
			},
			"asset": "mine_construction.svg",
			"order": 3
		},
		{
			"tileParts": {
				"top": 2100,
				"mid": 1000,
				"bot": -300,
				"left": 500,
				"right": 500
			},
			"asset": "bank.svg",
			"order": 3
		},
		{
			"tileParts": {
				"top": 500,
				"mid": 1000,
				"bot": 615,
				"left": 829,
				"right": 584
			},
			"asset": "mine_burst.svg",
			"order": 3
		}
		]
	},
	{
		"tileName": "springpadRight",
		"tileCode": "H",
		"tileTypes": [
		{
			"tileParts": {
				"top": 0,
				"mid": 1000,
				"bot": 1117,
				"left": 0,
				"right": 894
			},
			"asset": "spring_right.svg"
		}
		]
	},
	{
		"tileName": "springpadLeft",
		"tileCode": "G",
		"tileTypes": [
		{
			"tileParts": {
				"top": 0,
				"mid": 1000,
				"bot": 1117,
				"left": 0,
				"right": 894
			},
			"asset": "spring_left.svg"
		}
		]
	},
	{
		"tileName": "springpadBottom",
		"tileCode": "L",
		"tileTypes": [
		{
			"tileParts": {
				"top": 0,
				"mid": 1000,
				"bot": 1117,
				"left": 0,
				"right": 894
			},
			"asset": "spring_bottom.svg"
		}
		]
	},
	{
		"tileName": "springpadTop",
		"tileCode": "K",
		"tileTypes": [
		{
			"tileParts": {
				"top": 0,
				"mid": 1000,
				"bot": 1117,
				"left": 0,
				"right": 894
			},
			"asset": "spring_top.svg"
		}
		]
	},
	{
		"tileName": "springpadBottomRight",
		"tileCode": "P",
		"tileTypes": [
		{
			"tileParts": {
				"top": 0,
				"mid": 1000,
				"bot": 1117,
				"left": 0,
				"right": 894
			},
			"asset": "spring_bottom_right.svg"
		}
		]
	},
	{
		"tileName": "springpadTopLeft",
		"tileCode": "Z",
		"tileTypes": [
		{
			"tileParts": {
				"top": 0,
				"mid": 1000,
				"bot": 1117,
				"left": 0,
				"right": 894
			},
			"asset": "spring_top_left.svg"
		}
		]
	},
	{
		"tileName": "springpadBottomLeft",
		"tileCode": "O",
		"tileTypes": [
		{
			"tileParts": {
				"top": 0,
				"mid": 1000,
				"bot": 1117,
				"left": 0,
				"right": 894
			},
			"asset": "spring_bottom_left.svg"
		}
		]
	},
	{
		"tileName": "springpadTopRight",
		"tileCode": "U",
		"tileTypes": [
		{
			"tileParts": {
				"top": 0,
				"mid": 1000,
				"bot": 1117,
				"left": 0,
				"right": 894
			},
			"asset": "spring_top_right.svg"
		}
		]
	},
	{
		"tileName": "ikeRange",
		"tileCode": ",",
		"tileTypes": [
		{
			"tileParts": {
				"top": 12487,
				"mid": 1000,
				"bot": 525,
				"left": 11650,
				"right": 11667
			},
			"asset": "ike_blue_range.svg"
		},
		{
			"tileParts": {
				"top": 525,
				"mid": 1000,
				"bot": 12487,
				"left": 11650,
				"right": 11667
			},
			"asset": "ike_red_range.svg"
		}
		]
	},
	{
		"tileName": "rails",
		"tileCode": "Q",
		"tileTypes": [
		{
			"tileParts": {
				"top": 10343,
				"mid": 1000,
				"bot": 10265,
				"left": 10097,
				"right": 10270
			},
			"asset": "rails.svg"
		}
		]
	},
	{
		"tileName": "bench1",
		"tileCode": "E",
		"tileTypes": [
		{
			"tileParts": {
				"top": 438,
				"mid": 1000,
				"bot": 0,
				"left": 46,
				"right": 0
			},
			"asset": "bench_top_left.svg"
		},
		{
			"tileParts": {
				"top": 438,
				"mid": 1000,
				"bot": 0,
				"left": 0,
				"right": 46
			},
			"asset": "bench_top_right.svg"
		},
		{
			"tileParts": {
				"top": 302,
				"mid": 1000,
				"bot": 0,
				"left": 150,
				"right": 0
			},
			"asset": "bench_left_top.svg"
		},
		{
			"tileParts": {
				"top": 0,
				"mid": 1000,
				"bot": 243,
				"left": 150,
				"right": 0
			},
			"asset": "bench_left_bottom.svg"
		}
		],
		"tileLinks": {
			"rules": [
			{
				"condition": "***01***",
				"changeTileType": 1
			},
			{
				"condition": "***10***",
				"changeTileType": 2
			},
			{
				"condition": "*0****1*",
				"changeTileType": 3
			},
			{
				"condition": "*1****0*",
				"changeTileType": 4
			}
			],
			"multipleConditionsCouldApply": false,
			"edgeCase": 0,
			"defaults": {
				"tileType": 1
			}
		}
	},
	{
		"tileName": "bench2",
		"tileCode": "A",
		"tileTypes": [
		{
			"tileParts": {
				"top": 400,
				"mid": 1000,
				"bot": 243,
				"left": 46,
				"right": 0
			},
			"asset": "bench_bottom_left.svg"
		},
		{
			"tileParts": {
				"top": 400,
				"mid": 1000,
				"bot": 243,
				"left": 0,
				"right": 46
			},
			"asset": "bench_bottom_right.svg"
		},
		{
			"tileParts": {
				"top": 302,
				"mid": 1000,
				"bot": 0,
				"left": 0,
				"right": 150
			},
			"asset": "bench_right_top.svg"
		},
		{
			"tileParts": {
				"top": 0,
				"mid": 1000,
				"bot": 243,
				"left": 0,
				"right": 150
			},
			"asset": "bench_right_bottom.svg"
		}
		],
		"tileLinks": {
			"rules": [
			{
				"condition": "***01***",
				"changeTileType": 1
			},
			{
				"condition": "***10***",
				"changeTileType": 2
			},
			{
				"condition": "*0****1*",
				"changeTileType": 3
			},
			{
				"condition": "*1****0*",
				"changeTileType": 4
			}
			],
			"multipleConditionsCouldApply": false,
			"edgeCase": 0,
			"defaults": {
				"tileType": 1
			}
		}
	},
	{
		"tileName": "RopeFence",
		"tileCode": "a",
		"tileTypes": [
		{
			"tileParts": {
				"top": 500,
				"mid": 1000,
				"bot": 300,
				"left": 0,
				"right": 0
			},
			"asset": "rope_post.svg"
		},
		{
			"tileParts": {
				"top": 1325,
				"mid": 1000,
				"bot": 300,
				"left": 0,
				"right": 0
			},
			"asset": "rope_post_t.svg"
		},
		{
			"tileParts": {
				"top": 500,
				"mid": 1000,
				"bot": 300,
				"left": 0,
				"right": 500
			},
			"asset": "rope_post_r.svg"
		},
		{
			"tileParts": {
				"top": 1325,
				"mid": 1000,
				"bot": 300,
				"left": 0,
				"right": 500
			},
			"asset": "rope_post_tr.svg"
		},
		{
			"tileParts": {
				"top": 500,
				"mid": 1000,
				"bot": 300,
				"left": 0,
				"right": 0
			},
			"asset": "rope_post_mine.svg"
		},
		{
			"tileParts": {
				"top": 1325,
				"mid": 1000,
				"bot": 300,
				"left": 0,
				"right": 0
			},
			"asset": "rope_post_mine_t.svg"
		},
		{
			"tileParts": {
				"top": 500,
				"mid": 1000,
				"bot": 300,
				"left": 0,
				"right": 500
			},
			"asset": "rope_post_mine_r.svg"
		},
		{
			"tileParts": {
				"top": 1325,
				"mid": 1000,
				"bot": 300,
				"left": 0,
				"right": 500
			},
			"asset": "rope_post_mine_tr.svg"
		},
		{
			"tileParts": {
				"top": 500,
				"mid": 1000,
				"bot": 300,
				"left": 0,
				"right": 0
			},
			"asset": "rope_post_mortuary.svg"
		},
		{
			"tileParts": {
				"top": 1325,
				"mid": 1000,
				"bot": 300,
				"left": 0,
				"right": 0
			},
			"asset": "rope_post_mortuary_t.svg"
		},
		{
			"tileParts": {
				"top": 500,
				"mid": 1000,
				"bot": 300,
				"left": 0,
				"right": 500
			},
			"asset": "rope_post_mortuary_r.svg"
		},
		{
			"tileParts": {
				"top": 1325,
				"mid": 1000,
				"bot": 300,
				"left": 0,
				"right": 500
			},
			"asset": "rope_post_mortuary_tr.svg"
		},
		{
			"tileParts": {
				"top": 500,
				"mid": 1000,
				"bot": 300,
				"left": 0,
				"right": 0
			},
			"asset": "rope_post_giftshop.svg"
		},
		{
			"tileParts": {
				"top": 1325,
				"mid": 1000,
				"bot": 300,
				"left": 0,
				"right": 0
			},
			"asset": "rope_post_giftshop_t.svg"
		},
		{
			"tileParts": {
				"top": 500,
				"mid": 1000,
				"bot": 300,
				"left": 0,
				"right": 500
			},
			"asset": "rope_post_giftshop_r.svg"
		},
		{
			"tileParts": {
				"top": 1325,
				"mid": 1000,
				"bot": 300,
				"left": 0,
				"right": 500
			},
			"asset": "rope_post_giftshop_tr.svg"
		}
		],
		"tileLinks": {
			"rules": [
			{
				"condition": "*1**1***",
				"requiredBiome": 15,
				"changeTileType": 16
			},
			{
				"condition": "*0**1***",
				"requiredBiome": 15,
				"changeTileType": 15
			},
			{
				"condition": "*1**0***",
				"requiredBiome": 15,
				"changeTileType": 14
			},
			{
				"condition": "********",
				"requiredBiome": 15,
				"changeTileType": 13
			},
			{
				"condition": "*1**1***",
				"requiredBiome": 9,
				"changeTileType": 12
			},
			{
				"condition": "*0**1***",
				"requiredBiome": 9,
				"changeTileType": 11
			},
			{
				"condition": "*1**0***",
				"requiredBiome": 9,
				"changeTileType": 10
			},
			{
				"condition": "********",
				"requiredBiome": 9,
				"changeTileType": 9
			},
			{
				"condition": "*1**1***",
				"requiredBiome": 3,
				"changeTileType": 8
			},
			{
				"condition": "*0**1***",
				"requiredBiome": 3,
				"changeTileType": 7
			},
			{
				"condition": "*1**0***",
				"requiredBiome": 3,
				"changeTileType": 6
			},
			{
				"condition": "********",
				"requiredBiome": 3,
				"changeTileType": 5
			},
			{
				"condition": "*1**1***",
				"changeTileType": 4
			},
			{
				"condition": "*0**1***",
				"changeTileType": 3
			},
			{
				"condition": "*1**0***",
				"changeTileType": 2
			}
			],
			"multipleConditionsCouldApply": false,
			"edgeCase": 0,
			"defaults": {
				"tileType": 1
			}
		}
	}
	],
	"biomes": [
	{
		"name": "canyon",
		"color1": "237,158,110",
		"color2": "248,166,116",
		"defaults": [
		{
			"tile": "blocking1",
			"type": 1
		},
		{
			"tile": "blocking2",
			"type": 3
		},
		{
			"tile": "blocking3",
			"type": 1
		},
		{
			"tile": "blocking4",
			"type": 1
		},
		{
			"tile": "forest",
			"type": 1
		},
		{
			"tile": "respawningWall",
			"type": 1
		},
		{
			"tile": "blockingDestroyableWithWeapon",
			"type": 1
		},
		{
			"tile": "fence",
			"type": 1
		},
		{
			"tile": "water",
			"type": 1
		},
		{
			"tile": "player1",
			"type": 1
		},
		{
			"tile": "player2",
			"type": 1
		},
		{
			"tile": "objective",
			"type": 2
		},
		{
			"tile": "springpadRight",
			"type": 1
		},
		{
			"tile": "springpadLeft",
			"type": 1
		},
		{
			"tile": "springpadTop",
			"type": 1
		},
		{
			"tile": "springpadBottom",
			"type": 1
		},
		{
			"tile": "springpadTopLeft",
			"type": 1
		},
		{
			"tile": "springpadBottomRight",
			"type": 1
		},
		{
			"tile": "springpadTopRight",
			"type": 1
		},
		{
			"tile": "springpadBottomLeft",
			"type": 1
		},
		{
			"tile": "bench1",
			"type": 1
		},
		{
			"tile": "bench2",
			"type": 1
		},
		{
			"tile": "RopeFence",
			"type": 1
		}
		]
	},
	{
		"name": "jungle",
		"color1": "222,172,113",
		"color2": "234,180,118",
		"defaults": [
		{
			"tile": "blocking1",
			"type": 1
		},
		{
			"tile": "blocking2",
			"type": 2
		},
		{
			"tile": "blocking3",
			"type": 1
		},
		{
			"tile": "blocking4",
			"type": 1
		},
		{
			"tile": "forest",
			"type": 1
		},
		{
			"tile": "respawningWall",
			"type": 1
		},
		{
			"tile": "blockingDestroyableWithWeapon",
			"type": 1
		},
		{
			"tile": "fence",
			"type": 1
		},
		{
			"tile": "water",
			"type": 1
		},
		{
			"tile": "player1",
			"type": 1
		},
		{
			"tile": "player2",
			"type": 1
		},
		{
			"tile": "objective",
			"type": 2
		},
		{
			"tile": "springpadRight",
			"type": 1
		},
		{
			"tile": "springpadLeft",
			"type": 1
		},
		{
			"tile": "springpadTop",
			"type": 1
		},
		{
			"tile": "springpadBottom",
			"type": 1
		},
		{
			"tile": "springpadTopLeft",
			"type": 1
		},
		{
			"tile": "springpadBottomRight",
			"type": 1
		},
		{
			"tile": "springpadTopRight",
			"type": 1
		},
		{
			"tile": "springpadBottomLeft",
			"type": 1
		},
		{
			"tile": "bench1",
			"type": 1
		},
		{
			"tile": "bench2",
			"type": 1
		},
		{
			"tile": "RopeFence",
			"type": 1
		}
		]
	},
	{
		"name": "mine",
		"color1": "91,64,79",
		"color2": "96,68,83",
		"defaults": [
		{
			"tile": "blocking1",
			"type": 2
		},
		{
			"tile": "blocking2",
			"type": 1
		},
		{
			"tile": "blocking3",
			"type": 1
		},
		{
			"tile": "blocking4",
			"type": 1
		},
		{
			"tile": "forest",
			"type": 2
		},
		{
			"tile": "respawningWall",
			"type": 2
		},
		{
			"tile": "blockingDestroyableWithWeapon",
			"type": 2
		},
		{
			"tile": "fence",
			"type": 1
		},
		{
			"tile": "water",
			"type": 1
		},
		{
			"tile": "player1",
			"type": 1
		},
		{
			"tile": "player2",
			"type": 1
		},
		{
			"tile": "springpadRight",
			"type": 1
		},
		{
			"tile": "springpadLeft",
			"type": 1
		},
		{
			"tile": "springpadTop",
			"type": 1
		},
		{
			"tile": "springpadBottom",
			"type": 1
		},
		{
			"tile": "springpadTopLeft",
			"type": 1
		},
		{
			"tile": "springpadBottomRight",
			"type": 1
		},
		{
			"tile": "springpadTopRight",
			"type": 1
		},
		{
			"tile": "springpadBottomLeft",
			"type": 1
		},
		{
			"tile": "bench1",
			"type": 1
		},
		{
			"tile": "bench2",
			"type": 1
		},
		{
			"tile": "RopeFence",
			"type": 5
		}
		]
	},
	{
		"name": "canyon_showdown",
		"color1": "187,127,93",
		"color2": "198,135,98",
		"defaults": [
		{
			"tile": "blocking1",
			"type": 1
		},
		{
			"tile": "blocking2",
			"type": 3
		},
		{
			"tile": "blocking3",
			"type": 1
		},
		{
			"tile": "blocking4",
			"type": 1
		},
		{
			"tile": "forest",
			"type": 3
		},
		{
			"tile": "respawningWall",
			"type": 1
		},
		{
			"tile": "blockingDestroyableWithWeapon",
			"type": 2
		},
		{
			"tile": "fence",
			"type": 1
		},
		{
			"tile": "water",
			"type": 1
		},
		{
			"tile": "player1",
			"type": 1
		},
		{
			"tile": "player2",
			"type": 1
		},
		{
			"tile": "objective",
			"type": 2
		},
		{
			"tile": "springpadRight",
			"type": 1
		},
		{
			"tile": "springpadLeft",
			"type": 1
		},
		{
			"tile": "springpadTop",
			"type": 1
		},
		{
			"tile": "springpadBottom",
			"type": 1
		},
		{
			"tile": "springpadTopLeft",
			"type": 1
		},
		{
			"tile": "springpadBottomRight",
			"type": 1
		},
		{
			"tile": "springpadTopRight",
			"type": 1
		},
		{
			"tile": "springpadBottomLeft",
			"type": 1
		},
		{
			"tile": "bench1",
			"type": 1
		},
		{
			"tile": "bench2",
			"type": 1
		},
		{
			"tile": "RopeFence",
			"type": 1
		}
		]
	},
	{
		"name": "grassfield",
		"color1": "57,142,84",
		"color2": "60,150,88",
		"defaults": [
		{
			"tile": "blocking1",
			"type": 1
		},
		{
			"tile": "blocking2",
			"type": 3
		},
		{
			"tile": "blocking3",
			"type": 1
		},
		{
			"tile": "blocking4",
			"type": 1
		},
		{
			"tile": "forest",
			"type": 1
		},
		{
			"tile": "fence",
			"type": 1
		},
		{
			"tile": "water",
			"type": 1
		},
		{
			"tile": "player1",
			"type": 1
		},
		{
			"tile": "player2",
			"type": 1
		},
		{
			"tile": "springpadRight",
			"type": 1
		},
		{
			"tile": "springpadLeft",
			"type": 1
		},
		{
			"tile": "springpadTop",
			"type": 1
		},
		{
			"tile": "springpadBottom",
			"type": 1
		},
		{
			"tile": "springpadTopLeft",
			"type": 1
		},
		{
			"tile": "springpadBottomRight",
			"type": 1
		},
		{
			"tile": "springpadTopRight",
			"type": 1
		},
		{
			"tile": "springpadBottomLeft",
			"type": 1
		},
		{
			"tile": "bench1",
			"type": 1
		},
		{
			"tile": "bench2",
			"type": 1
		},
		{
			"tile": "RopeFence",
			"type": 1
		}
		]
	},
	{
		"name": "snowy",
		"color1": "45,154,242",
		"color2": "47,162,255",
		"defaults": [
		{
			"tile": "blocking1",
			"type": 3
		},
		{
			"tile": "blocking2",
			"type": 4
		},
		{
			"tile": "blocking3",
			"type": 2
		},
		{
			"tile": "blocking4",
			"type": 2
		},
		{
			"tile": "forest",
			"type": 4
		},
		{
			"tile": "respawningWall",
			"type": 3
		},
		{
			"tile": "blockingDestroyableWithWeapon",
			"type": 3
		},
		{
			"tile": "fence",
			"type": 1
		},
		{
			"tile": "water",
			"type": 1
		},
		{
			"tile": "player1",
			"type": 1
		},
		{
			"tile": "player2",
			"type": 1
		},
		{
			"tile": "springpadRight",
			"type": 1
		},
		{
			"tile": "springpadLeft",
			"type": 1
		},
		{
			"tile": "springpadTop",
			"type": 1
		},
		{
			"tile": "springpadBottom",
			"type": 1
		},
		{
			"tile": "springpadTopLeft",
			"type": 1
		},
		{
			"tile": "springpadBottomRight",
			"type": 1
		},
		{
			"tile": "springpadTopRight",
			"type": 1
		},
		{
			"tile": "springpadBottomLeft",
			"type": 1
		},
		{
			"tile": "bench1",
			"type": 1
		},
		{
			"tile": "bench2",
			"type": 1
		},
		{
			"tile": "RopeFence",
			"type": 1
		}
		]
	},
	{
		"name": "town",
		"color1": "140,84,109",
		"color2": "148,90,115",
		"defaults": [
		{
			"tile": "blocking1",
			"type": 4
		},
		{
			"tile": "blocking2",
			"type": 3
		},
		{
			"tile": "blocking3",
			"type": 1
		},
		{
			"tile": "blocking4",
			"type": 1
		},
		{
			"tile": "forest",
			"type": 1
		},
		{
			"tile": "respawningWall",
			"type": 4
		},
		{
			"tile": "blockingDestroyableWithWeapon",
			"type": 1
		},
		{
			"tile": "fence",
			"type": 4
		},
		{
			"tile": "water",
			"type": 1
		},
		{
			"tile": "player1",
			"type": 1
		},
		{
			"tile": "player2",
			"type": 1
		},
		{
			"tile": "objective",
			"type": 2
		},
		{
			"tile": "springpadRight",
			"type": 1
		},
		{
			"tile": "springpadLeft",
			"type": 1
		},
		{
			"tile": "springpadTop",
			"type": 1
		},
		{
			"tile": "springpadBottom",
			"type": 1
		},
		{
			"tile": "springpadTopLeft",
			"type": 1
		},
		{
			"tile": "springpadBottomRight",
			"type": 1
		},
		{
			"tile": "springpadTopRight",
			"type": 1
		},
		{
			"tile": "springpadBottomLeft",
			"type": 1
		},
		{
			"tile": "bench1",
			"type": 1
		},
		{
			"tile": "bench2",
			"type": 1
		},
		{
			"tile": "RopeFence",
			"type": 1
		}
		]
	},
	{
    	"name": "retro",
		"color1": "85,63,105",
		"color2": "90,66,111",
		"defaults": [
		{
			"tile": "blocking1",
			"type": 5
		},
		{
			"tile": "blocking2",
			"type": 5
		},
		{
			"tile": "blocking3",
			"type": 3
		},
		{
			"tile": "blocking4",
			"type": 3
		},
		{
			"tile": "forest",
			"type": 5
		},
		{
			"tile": "respawningWall",
			"type": 4
		},
		{
			"tile": "blockingDestroyableWithWeapon",
			"type": 4
		},
		{
			"tile": "fence",
			"type": 4
		},
		{
			"tile": "water",
			"type": 1
		},
		{
			"tile": "player1",
			"type": 1
		},
		{
			"tile": "player2",
			"type": 1
		},
		{
			"tile": "objective",
			"type": 2
		},
		{
			"tile": "springpadRight",
			"type": 1
		},
		{
			"tile": "springpadLeft",
			"type": 1
		},
		{
			"tile": "springpadTop",
			"type": 1
		},
		{
			"tile": "springpadBottom",
			"type": 1
		},
		{
			"tile": "springpadTopLeft",
			"type": 1
		},
		{
			"tile": "springpadBottomRight",
			"type": 1
		},
		{
			"tile": "springpadTopRight",
			"type": 1
		},
		{
			"tile": "springpadBottomLeft",
			"type": 1
		},
		{
			"tile": "bench1",
			"type": 1
		},
		{
			"tile": "bench2",
			"type": 1
		},
		{
			"tile": "RopeFence",
			"type": 1
		}
		]
	},
	{
    	"name": "mortuary",
		"color1": "70,49,78",
		"color2": "74,52,82",
		"defaults": [
		{
			"tile": "blocking1",
			"type": 6
		},
		{
			"tile": "blocking2",
			"type": 6
		},
		{
			"tile": "blocking3",
			"type": 4
		},
		{
			"tile": "blocking4",
			"type": 4
		},
		{
			"tile": "forest",
			"type": 6
		},
		{
			"tile": "respawningWall",
			"type": 5
		},
		{
			"tile": "blockingDestroyableWithWeapon",
			"type": 5
		},
		{
			"tile": "fence",
			"type": 4
		},
		{
			"tile": "water",
			"type": 1
		},
		{
			"tile": "player1",
			"type": 1
		},
		{
			"tile": "player2",
			"type": 1
		},
		{
			"tile": "objective",
			"type": 2
		},
		{
			"tile": "springpadRight",
			"type": 1
		},
		{
			"tile": "springpadLeft",
			"type": 1
		},
		{
			"tile": "springpadTop",
			"type": 1
		},
		{
			"tile": "springpadBottom",
			"type": 1
		},
		{
			"tile": "springpadTopLeft",
			"type": 1
		},
		{
			"tile": "springpadBottomRight",
			"type": 1
		},
		{
			"tile": "springpadTopRight",
			"type": 1
		},
		{
			"tile": "springpadBottomLeft",
			"type": 1
		},
		{
			"tile": "bench1",
			"type": 1
		},
		{
			"tile": "bench2",
			"type": 1
		},
		{
			"tile": "RopeFence",
			"type": 9
		}
		]
	},
	{
    	"name": "darryl",
		"color1": "213,116,84",
		"color2": "224,122,89",
		"defaults": [
		{
			"tile": "blocking1",
			"type": 7
		},
		{
			"tile": "blocking2",
			"type": 7
		},
		{
			"tile": "blocking3",
			"type": 1
		},
		{
			"tile": "blocking4",
			"type": 1
		},
		{
			"tile": "forest",
			"type": 7
		},
		{
			"tile": "respawningWall",
			"type": 6
		},
		{
			"tile": "blockingDestroyableWithWeapon",
			"type": 6
		},
		{
			"tile": "fence",
			"type": 4
		},
		{
			"tile": "water",
			"type": 1
		},
		{
			"tile": "player1",
			"type": 1
		},
		{
			"tile": "player2",
			"type": 1
		},
		{
			"tile": "objective",
			"type": 2
		},
		{
			"tile": "springpadRight",
			"type": 1
		},
		{
			"tile": "springpadLeft",
			"type": 1
		},
		{
			"tile": "springpadTop",
			"type": 1
		},
		{
			"tile": "springpadBottom",
			"type": 1
		},
		{
			"tile": "springpadTopLeft",
			"type": 1
		},
		{
			"tile": "springpadBottomRight",
			"type": 1
		},
		{
			"tile": "springpadTopRight",
			"type": 1
		},
		{
			"tile": "springpadBottomLeft",
			"type": 1
		},
		{
			"tile": "bench1",
			"type": 1
		},
		{
			"tile": "bench2",
			"type": 1
		},
		{
			"tile": "RopeFence",
			"type": 1
		}
		]
	},
	{
    	"name": "arcade",
		"color1": "47,42,75",
		"color2": "50,44,79",
		"defaults": [
		{
			"tile": "blocking1",
			"type": 8
		},
		{
			"tile": "blocking2",
			"type": 8
		},
		{
			"tile": "blocking3",
			"type": 1
		},
		{
			"tile": "blocking4",
			"type": 5
		},
		{
			"tile": "forest",
			"type": 1
		},
		{
			"tile": "respawningWall",
			"type": 7
		},
		{
			"tile": "blockingDestroyableWithWeapon",
			"type": 6
		},
		{
			"tile": "fence",
			"type": 4
		},
		{
			"tile": "water",
			"type": 1
		},
		{
			"tile": "player1",
			"type": 1
		},
		{
			"tile": "player2",
			"type": 1
		},
		{
			"tile": "objective",
			"type": 2
		},
		{
			"tile": "springpadRight",
			"type": 1
		},
		{
			"tile": "springpadLeft",
			"type": 1
		},
		{
			"tile": "springpadTop",
			"type": 1
		},
		{
			"tile": "springpadBottom",
			"type": 1
		},
		{
			"tile": "springpadTopLeft",
			"type": 1
		},
		{
			"tile": "springpadBottomRight",
			"type": 1
		},
		{
			"tile": "springpadTopRight",
			"type": 1
		},
		{
			"tile": "springpadBottomLeft",
			"type": 1
		},
		{
			"tile": "bench1",
			"type": 1
		},
		{
			"tile": "bench2",
			"type": 1
		},
		{
			"tile": "RopeFence",
			"type": 1
		}
		]
	},
	{
    	"name": "galaxy_arena",
		"color1": "57,142,84",
		"color2": "60,150,88",
		"defaults": [
		{
			"tile": "blocking1",
			"type": 8
		},
		{
			"tile": "blocking2",
			"type": 5
		},
		{
			"tile": "blocking3",
			"type": 5
		},
		{
			"tile": "blocking4",
			"type": 3
		},
		{
			"tile": "forest",
			"type": 1
		},
		{
			"tile": "respawningWall",
			"type": 7
		},
		{
			"tile": "blockingDestroyableWithWeapon",
			"type": 6
		},
		{
			"tile": "fence",
			"type": 4
		},
		{
			"tile": "water",
			"type": 1
		},
		{
			"tile": "player1",
			"type": 1
		},
		{
			"tile": "player2",
			"type": 1
		},
		{
			"tile": "objective",
			"type": 1
		},
		{
			"tile": "springpadRight",
			"type": 1
		},
		{
			"tile": "springpadLeft",
			"type": 1
		},
		{
			"tile": "springpadTop",
			"type": 1
		},
		{
			"tile": "springpadBottom",
			"type": 1
		},
		{
			"tile": "springpadTopLeft",
			"type": 1
		},
		{
			"tile": "springpadBottomRight",
			"type": 1
		},
		{
			"tile": "springpadTopRight",
			"type": 1
		},
		{
			"tile": "springpadBottomLeft",
			"type": 1
		},
		{
			"tile": "bench1",
			"type": 1
		},
		{
			"tile": "bench2",
			"type": 1
		},
		{
			"tile": "RopeFence",
			"type": 1
		}
		]
	},
	{
    	"name": "lamporium",
		"color1": "175,86,80",
		"color2": "188,90,87",
		"defaults": [
		{
			"tile": "blocking1",
			"type": 9
		},
		{
			"tile": "blocking2",
			"type": 9
		},
		{
			"tile": "blocking3",
			"type": 6
		},
		{
			"tile": "blocking4",
			"type": 6
		},
		{
			"tile": "forest",
			"type": 8
		},
		{
			"tile": "respawningWall",
			"type": 8
		},
		{
			"tile": "blockingDestroyableWithWeapon",
			"type": 2
		},
		{
			"tile": "fence",
			"type": 34
		},
		{
			"tile": "water",
			"type": 1
		},
		{
			"tile": "player1",
			"type": 1
		},
		{
			"tile": "player2",
			"type": 1
		},
		{
			"tile": "objective",
			"type": 2
		},
		{
			"tile": "springpadRight",
			"type": 1
		},
		{
			"tile": "springpadLeft",
			"type": 1
		},
		{
			"tile": "springpadTop",
			"type": 1
		},
		{
			"tile": "springpadBottom",
			"type": 1
		},
		{
			"tile": "springpadTopLeft",
			"type": 1
		},
		{
			"tile": "springpadBottomRight",
			"type": 1
		},
		{
			"tile": "springpadTopRight",
			"type": 1
		},
		{
			"tile": "springpadBottomLeft",
			"type": 1
		},
		{
			"tile": "bench1",
			"type": 1
		},
		{
			"tile": "bench2",
			"type": 1
		},
		{
			"tile": "RopeFence",
			"type": 1
		}
		]
	},
	{
    	"name": "mini",
		"color1": "57,57,81",
		"color2": "60,62,87",
		"defaults": [
		{
			"tile": "blocking1",
			"type": 10
		},
		{
			"tile": "blocking2",
			"type": 10
		},
		{
			"tile": "blocking3",
			"type": 7
		},
		{
			"tile": "blocking4",
			"type": 7
		},
		{
			"tile": "forest",
			"type": 9
		},
		{
			"tile": "respawningWall",
			"type": 9
		},
		{
			"tile": "blockingDestroyableWithWeapon",
			"type": 7
		},
		{
			"tile": "fence",
			"type": 44
		},
		{
			"tile": "water",
			"type": 1
		},
		{
			"tile": "player1",
			"type": 1
		},
		{
			"tile": "player2",
			"type": 1
		},
		{
			"tile": "objective",
			"type": 2
		},
		{
			"tile": "springpadRight",
			"type": 1
		},
		{
			"tile": "springpadLeft",
			"type": 1
		},
		{
			"tile": "springpadTop",
			"type": 1
		},
		{
			"tile": "springpadBottom",
			"type": 1
		},
		{
			"tile": "springpadTopLeft",
			"type": 1
		},
		{
			"tile": "springpadBottomRight",
			"type": 1
		},
		{
			"tile": "springpadTopRight",
			"type": 1
		},
		{
			"tile": "springpadBottomLeft",
			"type": 1
		},
		{
			"tile": "bench1",
			"type": 1
		},
		{
			"tile": "bench2",
			"type": 1
		},
		{
			"tile": "RopeFence",
			"type": 2
		}
		]
	},
	{
    	"name": "gift",
		"color1": "128,66,82",
		"color2": "133,70,86",
		"defaults": [
		{
			"tile": "blocking1",
			"type": 11
		},
		{
			"tile": "blocking2",
			"type": 11
		},
		{
			"tile": "blocking3",
			"type": 8
		},
		{
			"tile": "blocking4",
			"type": 7
		},
		{
			"tile": "forest",
			"type": 10
		},
		{
			"tile": "respawningWall",
			"type": 10
		},
		{
			"tile": "blockingDestroyableWithWeapon",
			"type": 8
		},
		{
			"tile": "fence",
			"type": 54
		},
		{
			"tile": "water",
			"type": 1
		},
		{
			"tile": "player1",
			"type": 1
		},
		{
			"tile": "player2",
			"type": 1
		},
		{
			"tile": "objective",
			"type": 2
		},
		{
			"tile": "springpadRight",
			"type": 1
		},
		{
			"tile": "springpadLeft",
			"type": 1
		},
		{
			"tile": "springpadTop",
			"type": 1
		},
		{
			"tile": "springpadBottom",
			"type": 1
		},
		{
			"tile": "springpadTopLeft",
			"type": 1
		},
		{
			"tile": "springpadBottomRight",
			"type": 1
		},
		{
			"tile": "springpadTopRight",
			"type": 1
		},
		{
			"tile": "springpadBottomLeft",
			"type": 1
		},
		{
			"tile": "bench1",
			"type": 1
		},
		{
			"tile": "bench2",
			"type": 1
		},
		{
			"tile": "RopeFence",
			"type": 13
		}
		]
	}
	],
	"gamemodes": [
	{
		"name": "Gem Grab",
		"specialTiles": [
		{
			"tile": "objective",
			"type": 1,
			"position": "m,m",
			"drawOrder": 2
		}
		]
	},
	{
		"name": "Bounty",
		"specialTiles": [
		{
			"tile": "objective",
			"type": 3,
			"position": "m,m",
			"drawOrder": 2
		}
		]
	},
	{
		"name": "Brawl Ball",
		"specialTiles": [
		{
			"tile": "objective",
			"type": 5,
			"position": "m,m",
			"drawOrder": 2
		},
		{
			"tile": "objective",
			"type": 6,
			"position": "m,2",
			"drawOrder": 2
		},
		{
			"tile": "objective",
			"type": 7,
			"position": "m,-2",
			"drawOrder": 2
		}
		]
	},
	{
		"name": "Showdown",
		"overrideBiome": [
		{
			"tile": "player1",
			"type": 2
		},
		{
			"tile": "player2",
			"type": 5
		}
		]
	},
	{
		"name": "Snowy Gem Grab",
		"specialTiles": [
		{
			"tile": "objective",
			"type": 8,
			"position": "m,m",
			"drawOrder": 2
		}
		]
	},
	{
		"name": "Big Game",
		"overrideBiome": [
		{
			"tile": "player1",
			"type": 2
		},
		{
			"tile": "player2",
			"type": 3
		}
		]
	},
	{
		"name": "Robo Rumble",
		"overrideBiome": [
		{
			"tile": "player1",
			"type": 1
		},
		{
			"tile": "player2",
			"type": 5
		}
		]
	},
	{
		"name": "Boss Fight",
		"overrideBiome": [
		{
			"tile": "player1",
			"type": 1
		},
		{
			"tile": "player2",
			"type": 4
		}
		]
	},
	{
		"name": "Siege",
		"overrideBiome": [
		{
			"tile": "objective",
			"type": 10
		}
		],
		"specialTiles": [
		{
			"tile": "ikeRange",
			"type": 1,
			"position": "m,-1",
			"drawOrder": 1
		},
		{
			"tile": "ikeRange",
			"type": 2,
			"position": "m,1",
			"drawOrder": 1
		}
		]
	},
	{
		"name": "Railed Gem Grab",
		"specialTiles": [
		{
			"tile": "objective",
			"type": 1,
			"position": "m,m",
			"drawOrder": 2
		},
		{
			"tile": "rails",
			"type": 1,
			"position": "m,m",
			"drawOrder": 1
		}
		]
	},
	{
		"name": "Town Gem Grab",
		"specialTiles": [
		{
			"tile": "objective",
			"type": 11,
			"position": "m,m",
			"drawOrder": 2
		}
		]
	},
	{
		"name": "Retro Gem Grab",
		"specialTiles": [
		{
			"tile": "objective",
			"type": 12,
			"position": "m,m",
			"drawOrder": 2
		}
		]
	},
	{
        "name": "Takedown",
        "overrideBiome": [
            {
                "tile": "player1",
                "type": 2
            },
            {
                "tile": "player2",
                "type": 5
            }
        ],
		"specialTiles": [
        {
            "tile": "player2",
            "type": 4,
            "position": "m,m",
            "drawOrder": 2
        }
		]
    },
    {
        "name": "Lone Star",
        "specialTiles": [
        {
            "tile": "objective",
            "type": 3,
            "position": "m,m",
            "drawOrder": 2
        }
        ]
    },
	{
		"name": "Mortuary Gem Grab",
		"specialTiles": [
		{
			"tile": "objective",
			"type": 13,
			"position": "m,m",
			"drawOrder": 2
		}
		]
	},
	{
		"name": "Darryl Gem Grab",
		"specialTiles": [
		{
			"tile": "objective",
			"type": 14,
			"position": "m,m",
			"drawOrder": 2
		}
		]
	},
	{
		"name": "Present Plunder",
		"overrideBiome": [
            {
                "tile": "objective",
                "type": 15
            }
        ]
	},
	{
		"name": "Hot Zone",
		"overrideBiome": [
            {
                "tile": "objective",
                "type": 17
            }
        ]
	},
	{
		"name": "PSG Brawl Ball",
		"specialTiles": [
		{
			"tile": "objective",
			"type": 18,
			"position": "m,m",
			"drawOrder": 2
		},
		{
			"tile": "objective",
			"type": 19,
			"position": "m,2",
			"drawOrder": 2
		},
		{
			"tile": "objective",
			"type": 20,
			"position": "m,-2",
			"drawOrder": 2
		}
		]
	},
	{
		"name": "Bazaar Gem Grab",
		"specialTiles": [
		{
			"tile": "objective",
			"type": 21,
			"position": "m,m",
			"drawOrder": 2
		}
		]
	},
	{
		"name": "Hot Zone (mod)",
		"overrideBiome": [
            {
                "tile": "objective",
                "type": 22
            }
        ]
	},
	{
		"name": "Super City Rampage",
		"overrideBiome": [
		{
			"tile": "player2",
			"type": 6
		}
		]
	},
	{
		"name": "Mini Gem Grab",
		"specialTiles": [
		{
			"tile": "objective",
			"type": 23,
			"position": "m,m",
			"drawOrder": 2
		}
		]
	},
	{
		"name": "Mini Heist",
		"overrideBiome": [
		{
			"tile": "objective",
			"type": 24
		}
		]
	},
	{
		"name": "Super City Rampage (mod)",
		"overrideBiome": [
		{
			"tile": "player2",
			"type": 7
		}
		]
	},
	{
		"name": "Gift Gem Grab",
		"specialTiles": [
		{
			"tile": "objective",
			"type": 25,
			"position": "m,m",
			"drawOrder": 2
		}
		]
	}
	]
}